processamento_basico_de_imagens/__init__.py
processamento_basico_de_imagens/processamento/__init__.py
processamento_basico_de_imagens/processamento/combinacao.py
processamento_basico_de_imagens/processamento/transformacao.py
processamento_basico_de_imagens/utilidades/__init__.py
processamento_basico_de_imagens/utilidades/io.py
processamento_basico_de_imagens/utilidades/plotagem.py
processamento_basico_de_imagens-0.0.1.dist-info/METADATA
processamento_basico_de_imagens-0.0.1.dist-info/WHEEL
processamento_basico_de_imagens-0.0.1.dist-info/top_level.txt
processamento_basico_de_imagens-0.0.1.dist-info/RECORD
