Metadata-Version: 2.1
Name: processamento-basico-de-imagens
Version: 0.0.1
Summary: Pacote de processamento de imagem com Skimage
Home-page: https://github.com/TMKaT/DIO/tree/main/Bootcamp%20Gera%C3%A7%C3%A3o%20Tech%20Unimed-BH%20-%20Ci%C3%AAncia%20de%20Dados/Desafios%20de%20projeto/Descomplicando%20a%20cria%C3%A7%C3%A3o%20de%20pacotes%20de%20processamento%20de%20imagens%20em%20Python
Author: Joadir D Junior
Author-email: junior.jdj@hotmail.com
Requires-Python: >=3.8
Requires-Dist: matplotlib
Requires-Dist: numpy
Requires-Dist: scikit-image (>=0.16.1)
